activegit/__init__.py
activegit/activegit.py
activegit-0.37.dist-info/DESCRIPTION.rst
activegit-0.37.dist-info/METADATA
activegit-0.37.dist-info/RECORD
activegit-0.37.dist-info/WHEEL
activegit-0.37.dist-info/entry_points.txt
activegit-0.37.dist-info/metadata.json
activegit-0.37.dist-info/top_level.txt
