Metadata-Version: 2.0
Name: activegit
Version: 0.37
Summary: Uses git for distributed active learning
Home-page: http://github.com/caseyjlaw/activegit
Author: Casey Law, Umaa Rebbapragada
Author-email: caseyjlaw@gmail.com
License: UNKNOWN
Platform: UNKNOWN
Requires-Dist: scikit-learn
Requires-Dist: sh
